rdiffb/__init__.py
rdiffb/bnode_mapper.py
rdiffb/canonicalizer_with_memory.py
rdiffb/rdiffb.py
rdiffb-0.5.0.data/scripts/rdfdiffb.py
rdiffb-0.5.0.dist-info/LICENSE
rdiffb-0.5.0.dist-info/METADATA
rdiffb-0.5.0.dist-info/WHEEL
rdiffb-0.5.0.dist-info/top_level.txt
rdiffb-0.5.0.dist-info/RECORD
